pydiscobasepro/__init__.py
pydiscobasepro/__main__.py
pydiscobasepro/cli/app.py
pydiscobasepro/cli/auth.py
pydiscobasepro/cli/benchmark.py
pydiscobasepro/cli/cli_commands.py
pydiscobasepro/cli/config.py
pydiscobasepro/cli/export_import.py
pydiscobasepro/cli/health.py
pydiscobasepro/cli/history.py
pydiscobasepro/cli/macros.py
pydiscobasepro/cli/metrics_viewer.py
pydiscobasepro/cli/plugins.py
pydiscobasepro/cli/sandbox.py
pydiscobasepro/cli/scheduler.py
pydiscobasepro/cli/snapshots.py
pydiscobasepro/cli/test_runner.py
pydiscobasepro/cli/workspaces.py
pydiscobasepro/cli/commands/__init__.py
pydiscobasepro/cli/commands/auth.py
pydiscobasepro/cli/commands/config_cmd.py
pydiscobasepro/cli/commands/devops.py
pydiscobasepro/cli/commands/monitoring.py
pydiscobasepro/cli/commands/plugins_cmd.py
pydiscobasepro/cli/commands/project.py
pydiscobasepro/cli/commands/testing.py
pydiscobasepro/core/audit.py
pydiscobasepro/core/automatic_test_discovery.py
pydiscobasepro/core/benchmark_framework.py
pydiscobasepro/core/builtin_metrics.py
pydiscobasepro/core/cache.py
pydiscobasepro/core/chaos_forensics.py
pydiscobasepro/core/ci_cd_templates.py
pydiscobasepro/core/config.py
pydiscobasepro/core/coverage_generator.py
pydiscobasepro/core/enterprise_platform.py
pydiscobasepro/core/event_tracing.py
pydiscobasepro/core/execution.py
pydiscobasepro/core/execution_timelines.py
pydiscobasepro/core/health_diagnostics.py
pydiscobasepro/core/hot_load_plugins.py
pydiscobasepro/core/intrusion_detection.py
pydiscobasepro/core/load_testing.py
pydiscobasepro/core/log_encryption.py
pydiscobasepro/core/log_rotation.py
pydiscobasepro/core/logging.py
pydiscobasepro/core/metrics.py
pydiscobasepro/core/mock_generator.py
pydiscobasepro/core/mutation_testing.py
pydiscobasepro/core/plugin_auto_update.py
pydiscobasepro/core/plugin_cli_injection.py
pydiscobasepro/core/plugin_crash_isolation.py
pydiscobasepro/core/plugin_dependencies.py
pydiscobasepro/core/plugin_marketplace.py
pydiscobasepro/core/plugin_metrics.py
pydiscobasepro-3.5.5.dist-info/licenses/LICENSE
pydiscobasepro-3.5.5.dist-info/METADATA
pydiscobasepro-3.5.5.dist-info/WHEEL
pydiscobasepro-3.5.5.dist-info/entry_points.txt
pydiscobasepro-3.5.5.dist-info/top_level.txt
pydiscobasepro-3.5.5.dist-info/RECORD
