Metadata-Version: 2.4
Name: pydiscobasepro
Version: 3.5.5
Summary: PyDiscoBasePro v3.5 - Enterprise-Grade Discord Bot Framework with 200+ Production-Grade Features
Author-email: Ramkrishna <ramkrishna@code-xon.fun>, Razzak <razzak@code-xon.fun>
License-Expression: MIT
Project-URL: Homepage, https://github.com/code-xon/pydiscobasepro
Project-URL: Repository, https://github.com/code-xon/pydiscobasepro.git
Project-URL: Documentation, https://pydiscobasepro.readthedocs.io/
Project-URL: Issues, https://github.com/code-xon/pydiscobasepro/issues
Project-URL: Changelog, https://github.com/code-xon/pydiscobasepro/blob/main/CHANGELOG.md
Keywords: discord,bot,framework,mongodb,python
Classifier: Development Status :: 5 - Production/Stable
Classifier: Intended Audience :: Developers
Classifier: Operating System :: OS Independent
Classifier: Programming Language :: Python :: 3
Classifier: Programming Language :: Python :: 3.11
Classifier: Programming Language :: Python :: 3.12
Classifier: Topic :: Software Development :: Libraries :: Python Modules
Classifier: Topic :: Communications :: Chat
Classifier: Topic :: System :: Distributed Computing
Classifier: Topic :: Security
Classifier: Topic :: System :: Monitoring
Requires-Python: >=3.11
License-File: LICENSE
Requires-Dist: discord.py>=2.3.0
Requires-Dist: motor>=3.3.0
Requires-Dist: loguru>=0.7.0
Requires-Dist: aiohttp>=3.9.0
Requires-Dist: watchfiles>=0.21.0
Requires-Dist: pymongo>=4.6.0
Requires-Dist: rich>=13.0.0
Requires-Dist: typer>=0.9.0
Requires-Dist: click>=8.0.0
Requires-Dist: prompt-toolkit>=3.0.0
Requires-Dist: cryptography>=41.0.0
Requires-Dist: bcrypt>=4.0.0
Requires-Dist: PyJWT>=2.8.0
Requires-Dist: prometheus-client>=0.19.0
Requires-Dist: structlog>=23.0.0
Requires-Dist: redis>=5.0.0
Requires-Dist: diskcache>=5.6.0
Requires-Dist: aiojobs>=1.2.0
Requires-Dist: celery>=5.3.0
Requires-Dist: pytest>=7.4.0
Requires-Dist: pytest-asyncio>=0.21.0
Requires-Dist: pytest-cov>=4.1.0
Requires-Dist: pytest-benchmark>=4.0.0
Requires-Dist: locust>=2.17.0
Requires-Dist: mutagen>=1.47.0
Requires-Dist: importlib-metadata>=6.0.0
Requires-Dist: docker>=6.1.0
Requires-Dist: kubernetes>=28.0.0
Requires-Dist: psutil>=5.9.0
Requires-Dist: memory-profiler>=0.61.0
Requires-Dist: pyyaml>=6.0.0
Requires-Dist: toml>=0.10.0
Requires-Dist: schedule>=1.2.0
Requires-Dist: colorama>=0.4.6
Requires-Dist: questionary>=2.0.0
Requires-Dist: tabulate>=0.9.0
Requires-Dist: tqdm>=4.65.0
Requires-Dist: croniter>=1.4.0
Requires-Dist: flask>=3.0.0
Requires-Dist: flask-login>=0.6.0
Requires-Dist: flask-wtf>=1.2.0
Requires-Dist: wtforms>=3.1.0
Requires-Dist: flask-socketio>=5.3.0
Requires-Dist: python-socketio>=5.10.0
Requires-Dist: python-engineio>=4.8.0
Requires-Dist: werkzeug>=3.0.0
Requires-Dist: jinja2>=3.1.0
Requires-Dist: markupsafe>=2.1.0
Requires-Dist: itsdangerous>=2.1.0
Requires-Dist: blinker>=1.7.0
Requires-Dist: aiohttp-cors>=0.7.0
Requires-Dist: pyopenssl>=23.3.0
Requires-Dist: cryptography>=41.0.0
Requires-Dist: certifi>=2023.11.0
Requires-Dist: ldap3>=2.9.0
Requires-Dist: pysaml2>=7.4.0
Requires-Dist: scim2-client>=0.1.0
Requires-Dist: policy-sentry>=0.12.0
Requires-Dist: chaostoolkit>=1.16.0
Requires-Dist: chaostoolkit-kubernetes>=0.29.0
Requires-Dist: chaostoolkit-aws>=0.25.0
Requires-Dist: volatility3>=2.5.0
Requires-Dist: yara-python>=4.3.0
Requires-Dist: python-magic>=0.4.0
Requires-Dist: compliance-trestle>=2.4.0
Requires-Dist: oscrypto>=1.3.0
Requires-Dist: asn1crypto>=1.5.0
Dynamic: license-file
